glQiwiApi/__init__.py
glQiwiApi/contrib/__init__.py
glQiwiApi/core/__init__.py
glQiwiApi/core/abc/__init__.py
glQiwiApi/core/abc/api_method.py
glQiwiApi/core/abc/base_api_client.py
glQiwiApi/core/cache/__init__.py
glQiwiApi/core/cache/cached_types.py
glQiwiApi/core/cache/constants.py
glQiwiApi/core/cache/exceptions.py
glQiwiApi/core/cache/invalidation.py
glQiwiApi/core/cache/storage.py
glQiwiApi/core/cache/utils.py
glQiwiApi/core/event_fetching/__init__.py
glQiwiApi/core/event_fetching/class_based/__init__.py
glQiwiApi/core/event_fetching/class_based/base.py
glQiwiApi/core/event_fetching/class_based/bill.py
glQiwiApi/core/event_fetching/class_based/error.py
glQiwiApi/core/event_fetching/class_based/transaction.py
glQiwiApi/core/event_fetching/class_based/webhook_transaction.py
glQiwiApi/core/event_fetching/dispatcher.py
glQiwiApi/core/event_fetching/executor.py
glQiwiApi/core/event_fetching/filters.py
glQiwiApi/core/event_fetching/webhooks/__init__.py
glQiwiApi/core/event_fetching/webhooks/app.py
glQiwiApi/core/event_fetching/webhooks/config.py
glQiwiApi/core/event_fetching/webhooks/dto/__init__.py
glQiwiApi/core/event_fetching/webhooks/dto/errors.py
glQiwiApi/core/event_fetching/webhooks/middlewares/__init__.py
glQiwiApi/core/event_fetching/webhooks/middlewares/ip.py
glQiwiApi/core/event_fetching/webhooks/services/__init__.py
glQiwiApi/core/event_fetching/webhooks/services/collision_detector.py
glQiwiApi/core/event_fetching/webhooks/services/security/__init__.py
glQiwiApi/core/event_fetching/webhooks/services/security/ip.py
glQiwiApi/core/event_fetching/webhooks/utils.py
glQiwiApi/core/event_fetching/webhooks/views/__init__.py
glQiwiApi/core/event_fetching/webhooks/views/base.py
glQiwiApi/core/event_fetching/webhooks/views/bill_view.py
glQiwiApi/core/event_fetching/webhooks/views/transaction_view.py
glQiwiApi/core/request_service.py
glQiwiApi/core/session/__init__.py
glQiwiApi/core/session/holder.py
glQiwiApi/ext/__init__.py
glQiwiApi/ext/webhook_url.py
glqiwiapi-2.18.3.dist-info/LICENSE
glqiwiapi-2.18.3.dist-info/WHEEL
glqiwiapi-2.18.3.dist-info/METADATA
glqiwiapi-2.18.3.dist-info/RECORD
