Metadata-Version: 2.1
Name: glqiwiapi
Version: 2.18.3
Summary: The ultrarapid and multifunctional wrapper over QIWI and YooMoney
Home-page: https://github.com/GLEF1X/glQiwiApi
License: MIT
Keywords: qiwi,yoomoney,api,yoo_money,wrapper,asyncio
Author: Glib Garanin
Author-email: glebgar567@gmail.com
Maintainer: GLEF1X
Maintainer-email: glebgar567@gmail.com
Requires-Python: >=3.7,<4.0
Classifier: Development Status :: 5 - Production/Stable
Classifier: Environment :: Console
Classifier: Framework :: AsyncIO
Classifier: Intended Audience :: Developers
Classifier: Intended Audience :: System Administrators
Classifier: License :: OSI Approved :: MIT License
Classifier: Programming Language :: Python :: 3
Classifier: Programming Language :: Python :: 3.7
Classifier: Programming Language :: Python :: 3.8
Classifier: Programming Language :: Python :: 3.9
Classifier: Programming Language :: Python :: 3.10
Classifier: Programming Language :: Python :: 3.11
Classifier: Programming Language :: Python :: 3.10
Classifier: Programming Language :: Python :: 3.11
Classifier: Programming Language :: Python :: 3.7
Classifier: Programming Language :: Python :: 3.8
Classifier: Programming Language :: Python :: 3.9
Classifier: Topic :: Software Development :: Libraries :: Application Frameworks
Classifier: Typing :: Typed
Provides-Extra: docs
Provides-Extra: fast
Requires-Dist: Sphinx (>=4.3.2,<5.0.0); extra == "docs"
Requires-Dist: Sphinx-Substitution-Extensions (>=2020.9.30,<2023.0.0); extra == "docs"
Requires-Dist: aiofiles (>=22.1.0,<23.0.0); extra == "fast"
Requires-Dist: aiohttp (>=3.8.3,<4.0.0)
Requires-Dist: backports.zoneinfo (>=0.2.1,<0.3.0); python_version < "3.9"
Requires-Dist: furo (>=2022.2.23,<2023.0.0); extra == "docs"
Requires-Dist: markdown-include (>=0.6,<0.8); extra == "docs"
Requires-Dist: pydantic (>=1.10.2,<2.0.0)
Requires-Dist: pygments (>=2.4,<3.0); extra == "docs"
Requires-Dist: pymdown-extensions (>=9.4,<10.0); extra == "docs"
Requires-Dist: sphinx-autobuild (>=2021.3.14,<2022.0.0); extra == "docs"
Requires-Dist: sphinx-copybutton (>=0.5.0,<0.6.0); extra == "docs"
Requires-Dist: sphinx-intl (>=2.0.1,<3.0.0); extra == "docs"
Requires-Dist: sphinx-notfound-page; extra == "docs"
Requires-Dist: sphinx-prompt (>=1.5.0,<2.0.0); extra == "docs"
Requires-Dist: sphinxemoji; extra == "docs"
Requires-Dist: towncrier (>=21.9.0,<22.0.0); extra == "docs"
Requires-Dist: typing_extensions (>=4.0.1,<5.0.0); python_full_version <= "3.7.0"
Requires-Dist: tzdata (>=2022.6,<2023.0)
Requires-Dist: uvloop (>=0.16.0,<0.17.0); (sys_platform == "darwin" or sys_platform == "linux") and (extra == "fast")
Project-URL: Documentation, https://glqiwiapi.readthedocs.io/en/latest/
Project-URL: Repository, https://github.com/GLEF1X/glQiwiApi
